cli.py
safeops_cli-0.1.6.dist-info/entry_points.txt
safeops_cli-0.1.6.dist-info/WHEEL
safeops_cli-0.1.6.dist-info/METADATA
safeops_cli-0.1.6.dist-info/RECORD
