Metadata-Version: 2.1
Name: safeops-cli
Version: 0.1.6
Summary: 
Author: Andres moreno
Author-email: amoreno@opsline.com
Requires-Python: >=3.6,<4.0
Classifier: Programming Language :: Python :: 3
Classifier: Programming Language :: Python :: 3.6
Classifier: Programming Language :: Python :: 3.7
Classifier: Programming Language :: Python :: 3.8
Classifier: Programming Language :: Python :: 3.9
Requires-Dist: click (>=7.1.2,<8.0.0)
Requires-Dist: funcy (>=1.15,<2.0)
Requires-Dist: requests (>=2.25.1,<3.0.0)
